{
    "header" : {
        "text" : "Let's see some of my work!",
        "colored" : "work!",
        "color" : "text-emerald-500"
    },
    "projects" : [
        {
            "title" : "Bavard a twitter clone",
            "description" :"A twitter clone created with react js for front-end and supabase as back-end. it’s Auth protected and users can create , view , repost , reply and remove posts, following and viewing profiles are exists too  but massaging will be added soon",
            "technologies" : ["react", "vite", "supabase","tailwind"],
            "image" : "/images/Bavard.png",
            "color" : {
                "backdrop" : "bg-violet-600",
                "background" : "bg-violet-500"
            },
            "demo" : "https://bavard.vercel.app",
            "github" : ""
        },
        {
            "title" : "Personal portfolio",
            "description" :"Crafted with Next.js, my personal portfolio serves as a platform for showcasing my diverse skillset.",
            "technologies" : ["next", "tailwind"],
            "image" : "/images/Portfolio.png",
            "color" : {
                "backdrop" : "bg-cyan-600",
                "background" : "bg-cyan-500"
            },
            "demo" : "https://mmdjamali.ir",
            "github" : ""
        },
        {
            "title" : "Classic tetris",
            "description" :"Experience the nostalgia of Classic Tetris, built with React, it's responsive for seamless gameplay on both desktop and mobile devices.",
            "technologies" : ["react"],
            "image" : "/images/Tetris.png",
            "color" : {
                "backdrop" : "bg-green-600",
                "background" : "bg-green-500"
            },
            "demo" : "https://1stmmd-tetris.vercel.app/",
            "github" : ""
        }
    ]
}